tomo3d/__init__.py
tomo3d/bibtex.py
tomo3d/constants.py
tomo3d/protocols.conf
tomo3d/protocols/__init__.py
tomo3d/protocols/protocol_align_ts.py
tomo3d/protocols/protocol_base.py
tomo3d/protocols/protocol_denoise_tomogram.py
tomo3d/protocols/protocol_motion_compensation.py
tomo3d/protocols/protocol_reconstruct_tomogram.py
tomo3d/tests/__init__.py
tomo3d/tests/_test_protocol_alignts.py
tomo3d/tests/test_protocol_denoise_tomogram.py
tomo3d/tests/test_protocol_reconstruct_tomogram.py
scipion_em_tomo3d-3.3.0.dist-info/LICENSE
scipion_em_tomo3d-3.3.0.dist-info/METADATA
scipion_em_tomo3d-3.3.0.dist-info/WHEEL
scipion_em_tomo3d-3.3.0.dist-info/entry_points.txt
scipion_em_tomo3d-3.3.0.dist-info/top_level.txt
scipion_em_tomo3d-3.3.0.dist-info/RECORD
